tfdatacompose-0.1.0.dist-info/METADATA
tfdatacompose-0.1.0.dist-info/WHEEL
tfdatacompose-0.1.0.dist-info/entry_points.txt
tfdatacompose-0.1.0.dist-info/licenses/LICENSE
tfdatacompose/__init__.py
tfdatacompose/batch.py
tfdatacompose/datasetoperation.py
tfdatacompose/filter/__init__.py
tfdatacompose/filter/filter.py
tfdatacompose/filter/numpyfilter.py
tfdatacompose/filter/pythonfunctionfilter.py
tfdatacompose/flatmap.py
tfdatacompose/lambdamap/__init__.py
tfdatacompose/lambdamap/lambdamap.py
tfdatacompose/lambdamap/numpylambdamap.py
tfdatacompose/lambdamap/pythonfunctionlambdamap.py
tfdatacompose/map/__init__.py
tfdatacompose/map/map.py
tfdatacompose/map/numpymap.py
tfdatacompose/map/pythonfunctionmap.py
tfdatacompose/pipeline.py
tfdatacompose/skip.py
tfdatacompose/take.py
tfdatacompose/util/__init__.py
tfdatacompose/util/print.py
tfdatacompose/util/printshape.py
tfdatacompose-0.1.0.dist-info/RECORD
